parse_ingredient/__init__.py
parse_ingredient/ingredient.py
parse_ingredient/internal/__init__.py
parse_ingredient/internal/client.py
zestful_parse_ingredient-0.0.7.dist-info/LICENSE
zestful_parse_ingredient-0.0.7.dist-info/METADATA
zestful_parse_ingredient-0.0.7.dist-info/WHEEL
zestful_parse_ingredient-0.0.7.dist-info/top_level.txt
zestful_parse_ingredient-0.0.7.dist-info/RECORD
