Metadata-Version: 2.1
Name: zestful-parse-ingredient
Version: 0.0.7
Summary: Parse recipe ingredients into structured data (name, quantity, units, preparation notes)
Home-page: https://github.com/mtlynch/zestful-client.git
Author: Michael Lynch
Author-email: michael@zestfuldata.com
License: MIT
Project-URL: repository, https://github.com/mtlynch/zestful-client
Keywords: ingredients ingredient parsing recipes nlp zestful
Platform: UNKNOWN
Requires-Python: >=3.7
